[
  {
    "Type": "CompositeItemMetadata",
    "Name": "CompositeItemMetadata_0",
    "Outer": "HT_Perk_HackedCratesExplode_010",
    "Class": "UScriptClass'CompositeItemMetadata'",
    "Properties": {
      "Metadata": [
        {
          "ObjectName": "GameplayEffectMetadata'HT_Perk_HackedCratesExplode_010:CompositeItemMetadata_0.GameplayEffectMetadata_0'",
          "ObjectPath": "TheExit/Content/Items/Hunters/Character/Items_Released/Perks/TheVeteran/HT_Perk_HackedCratesExplode_010.1"
        }
      ]
    }
  },
  {
    "Type": "GameplayEffectMetadata",
    "Name": "GameplayEffectMetadata_0",
    "Outer": "CompositeItemMetadata_0",
    "Class": "UScriptClass'GameplayEffectMetadata'",
    "Properties": {
      "GameplayEffect": {
        "ObjectName": "BlueprintGeneratedClass'PerkMod_HackedCratesExplode_C'",
        "ObjectPath": "TheExit/Content/Items/GameplayEffects/Hunter/PerkMod_HackedCratesExplode.0"
      },
      "Level": 9.0
    }
  },
  {
    "Type": "LoadoutItemAsset",
    "Name": "HT_Perk_HackedCratesExplode_010",
    "Class": "UScriptClass'LoadoutItemAsset'",
    "Properties": {
      "DeploymentMode": "EDeploymentMode::Released",
      "ItemImage": {
        "ObjectName": "Texture2D'PerksPowerIcon_Hunter_TheVeteran_AboutToBlow'",
        "ObjectPath": "TheExit/Content/UI/ImageAssets/GameIcons/HunterPerks/TheVeteran/PerksPowerIcon_Hunter_TheVeteran_AboutToBlow.0"
      },
      "DefaultCost": [
        {
          "CurrencyId": "EGMCurrency::CurrencyB",
          "Price": 1720
        },
        {
          "CurrencyId": "EGMCurrency::CurrencyA",
          "Price": 1059
        }
      ],
      "RequiredChallengesToComplete": [
        {
          "ChallengeId": "0DEBB341-41DD7D71-9EE5C199-707ED8E4",
          "ChallengeCompletionValue": 150.0,
          "ChallengeAsset": {
            "AssetPathName": "/Game/Challenges/Progression/Challenge_HackedCratesExplode_Hunter.Challenge_HackedCratesExplode_Hunter",
            "SubPathString": ""
          }
        }
      ],
      "ItemEffectDescriptions": [
        {
          "FormatedDescription": {
            "TableId": "/Game/StringTables/Characters.Characters",
            "Key": "Runner_SawboneWeaponHeal001_ItemEffectDESC"
          },
          "Arguments": [
            57.0
          ]
        }
      ],
      "DisplayName": {
        "TableId": "/Game/StringTables/Perks.Perks",
        "Key": "Veteran_HackerCrateExplode_NAME"
      },
      "Description": {
        "TableId": "/Game/StringTables/Perks.Perks",
        "Key": "Veteran_HackerCrateExplode_DESC"
      },
      "LoreText": {
        "TableId": "/Game/StringTables/Perks.Perks",
        "Key": "Veteran_HackerCrateExplode_LORE"
      },
      "Guid": "4EEC7CAE-43770244-7F22A5B4-F316B988",
      "TagContainer": [
        "Accessory.Trinket",
        "Accessory.Perk"
      ],
      "TagQuery": {
        "TagDictionary": [
          {
            "TagName": "Class.Hunter"
          }
        ],
        "QueryTokenStream": [
          0,
          1,
          2,
          1,
          0
        ],
        "AutoDescription": " ALL( Class.Hunter )"
      },
      "Metadata": {
        "ObjectName": "CompositeItemMetadata'HT_Perk_HackedCratesExplode_010:CompositeItemMetadata_0'",
        "ObjectPath": "TheExit/Content/Items/Hunters/Character/Items_Released/Perks/TheVeteran/HT_Perk_HackedCratesExplode_010.0"
      },
      "Version": 1
    }
  }
]
