[
  {
    "Type": "BP_Ability_Item_C",
    "Name": "HT_SpawnTurretPower_006",
    "Class": "BlueprintGeneratedClass'TheExit/Content/Items/ItemTemplates/Powers/BP_Ability_Item.BP_Ability_Item_C'",
    "Template": {
      "ObjectName": "BP_Ability_Item_C'Default__BP_Ability_Item_C'",
      "ObjectPath": "TheExit/Content/Items/ItemTemplates/Powers/BP_Ability_Item.1"
    },
    "Properties": {
      "ActorClass": {
        "AssetPathName": "/Game/Items/ItemTemplates/Powers/SpawnTurret/BP_SpawnTurret.BP_SpawnTurret_C",
        "SubPathString": ""
      },
      "DeploymentMode": "EDeploymentMode::Released",
      "ItemImage": {
        "ObjectName": "Texture2D'PerksPowerIcon_Hunter_TheInquisitor_Turrets'",
        "ObjectPath": "TheExit/Content/UI/ImageAssets/GameIcons/HunterPerks/TheInquisitor/PerksPowerIcon_Hunter_TheInquisitor_Turrets.0"
      },
      "DefaultCost": [
        {
          "CurrencyId": "EGMCurrency::CurrencyC",
          "Price": 1100
        },
        {
          "CurrencyId": "EGMCurrency::CurrencyA",
          "Price": 183
        }
      ],
      "FollowingItem": {
        "ObjectName": "BP_Ability_Item_C'HT_SpawnTurretPower_007'",
        "ObjectPath": "TheExit/Content/Items/Hunters/Character/Items_Released/Powers/HT_SpawnTurretPower_007.0"
      },
      "RequiredChallengesToComplete": [
        {
          "ChallengeId": "F13B9B0F-4BF97BB9-C7023F90-EF1C0594",
          "ChallengeCompletionValue": 375.0,
          "ChallengeAsset": {
            "AssetPathName": "/Game/Challenges/Progression/Challenge_Turrets_Hunter.Challenge_Turrets_Hunter",
            "SubPathString": ""
          }
        }
      ],
      "ItemEffectDescriptions": [
        {
          "FormatedDescription": {
            "TableId": "/Game/StringTables/Characters.Characters",
            "Key": "Hunter_SpawnTurret_FormatedDESC"
          },
          "Arguments": [
            43.0
          ]
        }
      ],
      "DisplayName": {
        "TableId": "/Game/StringTables/Characters.Characters",
        "Key": "Hunter_SpawnTurret_DisplayName"
      },
      "Description": {
        "TableId": "/Game/StringTables/Characters.Characters",
        "Key": "Hunter_SpawnTurret_DESC"
      },
      "LoreText": {
        "TableId": "/Game/StringTables/Characters.Characters",
        "Key": "Hunter_SpawnTurret_LORE"
      },
      "Guid": "A4A8A2AC-4F284D8E-3D837591-478FD910",
      "TagContainer": [
        "Ability.SpawnTurret"
      ],
      "Metadata": {
        "ObjectName": "WeaponModsMetadata'HT_SpawnTurretPower_006:WeaponModsMetadata_0'",
        "ObjectPath": "TheExit/Content/Items/Hunters/Character/Items_Released/Powers/HT_SpawnTurretPower_006.2"
      },
      "NativeClass": {
        "ObjectName": "BlueprintGeneratedClass'BP_Ability_Item_C'",
        "ObjectPath": "TheExit/Content/Items/ItemTemplates/Powers/BP_Ability_Item.0"
      }
    }
  },
  {
    "Type": "PowerLevelMod",
    "Name": "PowerLevelMod_0",
    "Outer": "WeaponModsMetadata_0",
    "Class": "UScriptClass'PowerLevelMod'",
    "Properties": {
      "Level": 5
    }
  },
  {
    "Type": "WeaponModsMetadata",
    "Name": "WeaponModsMetadata_0",
    "Outer": "HT_SpawnTurretPower_006",
    "Class": "UScriptClass'WeaponModsMetadata'",
    "Properties": {
      "WeaponMods": [
        {
          "ObjectName": "PowerLevelMod'HT_SpawnTurretPower_006:WeaponModsMetadata_0.PowerLevelMod_0'",
          "ObjectPath": "TheExit/Content/Items/Hunters/Character/Items_Released/Powers/HT_SpawnTurretPower_006.1"
        }
      ],
      "RequiredTags": [
        "Ability.SpawnTurret"
      ]
    }
  }
]